lalafo_api/__init__.py
lalafo_api/enums.py
lalafo_api/exceptions.py
lalafo_api/api/__init__.py
lalafo_api/api/async_lalafo_client.py
lalafo_api/api/base_lalafo_client.py
lalafo_api/api/clients.py
lalafo_api/api/lalafo_client.py
lalafo_api/models/__init__.py
lalafo_api/models/ad_models.py
lalafo_api/models/base_models.py
lalafo_api/models/category_models.py
lalafo_api/models/filter_models.py
lalafo_api/models/request_models.py
lalafo_api/models/response_models.py
lalafo_api/utils/__init__.py
lalafo_api/utils/ad_utils.py
lalafo_api/utils/url_utils.py
lalafo_api-0.1.0.dist-info/METADATA
lalafo_api-0.1.0.dist-info/WHEEL
lalafo_api-0.1.0.dist-info/top_level.txt
lalafo_api-0.1.0.dist-info/RECORD
