Metadata-Version: 2.4
Name: lalafo_api
Version: 0.1.0
Summary: Библиотека для работы с API Lalafo
Author: Umar
License: Proprietary
Project-URL: Homepage, https://github.com/Umar151515/lalafo-api
Project-URL: Repository, https://github.com/Umar151515/lalafo-api
Platform: any
Requires-Python: >=3.8
Requires-Dist: httpx<1.0.0
Requires-Dist: pydantic>=2.0
